codes/atan_rom.v
//ARCTAN ROM ITERATION VALUES MODULE

module atan_rom #(WIDTH = 16,
                  ADDR_WIDTH = 4)
                 (input [ADDR_WIDTH-1 : 0] addr,
                  output reg signed [WIDTH-1 : 0] angle);
    
    always @(*) begin

        case(addr) //Q3.13 fixed point values for each iteration

            4'd0: angle = 16'h1922;
            4'd1: angle = 16'h0ED6;
            4'd2: angle = 16'h07D7;
            4'd3: angle = 16'h03FB;
            4'd4: angle = 16'h01FF;
            4'd5: angle = 16'h0100;
            4'd6: angle = 16'h0080;
            4'd7: angle = 16'h0040;
            4'd8: angle = 16'h0020;
            4'd9: angle = 16'h0010;
            4'd10: angle = 16'h0008;
            4'd11: angle = 16'h0004;
            4'd12: angle = 16'h0002;
            4'd13: angle = 16'h0001;
            4'd14: angle = 16'h0000;
            4'd15: angle = 16'h0000;
        endcase
    end

endmodule

tb/atan_rom_tb.v
//ARCTAN ROM TB
module atan_rom_test;

parameter WIDTH = 16;
parameter ADDR_WIDTH = 4;

reg [ADDR_WIDTH-1 : 0] addr;

wire signed [WIDTH-1 : 0] angle;

integer i;

atan_rom uut(.addr(addr),
             .angle(angle));
    
    initial begin

        $dumpfile("dump_rom.vcd");
        $dumpvars(0, atan_rom_test);

        for(i=0 ; i<16 ; i=i+1) begin

            addr = i;
            #10;

            $display("|    %2d    |    %5d    |    %h    |", addr, angle, angle);
        end
    
    end

endmodule

simulation/dump_rom.vcd
$date
	Sat Jul 18 19:49:31 2026
$end
$version
	Icarus Verilog
$end
$timescale
	1s
$end
$scope module atan_rom_test $end
$var wire 16 ! angle [15:0] $end
$var parameter 32 " ADDR_WIDTH $end
$var parameter 32 # WIDTH $end
$var reg 4 $ addr [3:0] $end
$var integer 32 % i [31:0] $end
$scope module uut $end
$var wire 4 & addr [3:0] $end
$var parameter 32 ' ADDR_WIDTH $end
$var parameter 32 ( WIDTH $end
$var reg 16 ) angle [15:0] $end
$upscope $end
$upscope $end
$enddefinitions $end
$comment Show the parameter values. $end
$dumpall
b10000 (
b100 '
b10000 #
b100 "
$end
#0
$dumpvars
b1100100100010 )
b0 &
b0 %
b0 $
b1100100100010 !
$end
#10
b111011010110 !
b111011010110 )
b1 $
b1 &
b1 %
#20
b11111010111 !
b11111010111 )
b10 $
b10 &
b10 %
#30
b1111111011 !
b1111111011 )
b11 $
b11 &
b11 %
#40
b111111111 !
b111111111 )
b100 $
b100 &
b100 %
#50
b100000000 !
b100000000 )
b101 $
b101 &
b101 %
#60
b10000000 !
b10000000 )
b110 $
b110 &
b110 %
#70
b1000000 !
b1000000 )
b111 $
b111 &
b111 %
#80
b100000 !
b100000 )
b1000 $
b1000 &
b1000 %
#90
b10000 !
b10000 )
b1001 $
b1001 &
b1001 %
#100
b1000 !
b1000 )
b1010 $
b1010 &
b1010 %
#110
b100 !
b100 )
b1011 $
b1011 &
b1011 %
#120
b10 !
b10 )
b1100 $
b1100 &
b1100 %
#130
b1 !
b1 )
b1101 $
b1101 &
b1101 %
#140
b0 !
b0 )
b1110 $
b1110 &
b1110 %
#150
b1111 $
b1111 &
b1111 %
#160
b10000 %
